{
  "appPageId" : "fb6e5011-0cd8-4f43-bc2b-4b3eae56e8dc",
  "componentName" : "siteforce:sldsOneColLayout",
  "dataProviders" : [ ],
  "id" : "e722cce9-54ca-4783-85aa-ed30843aaf17",
  "label" : "Record Detail",
  "regions" : [ {
    "id" : "5b7eeabd-a8bf-4955-941b-d829e00827f7",
    "regionName" : "header",
    "type" : "region"
  }, {
    "components" : [ {
      "componentAttributes" : {
        "recordId" : "{!recordId}"
      },
      "componentName" : "forceCommunity:recordHeadline",
      "id" : "4722857e-3cd7-4c98-bdf5-3366b2527c99",
      "renderPriority" : "NEUTRAL",
      "renditionMap" : { },
      "type" : "component"
    }, {
      "componentAttributes" : {
        "detailsTabLabel" : "Details",
        "discussionsTabLabel" : "Feed",
        "recordId" : "{!recordId}",
        "relatedTabLabel" : "Related",
        "showLegacyActivityComposer" : false,
        "tab1Type" : "details",
        "tab2Type" : "related",
        "tab3Type" : "chatter",
        "tab4Type" : "none",
        "timelineTabLabel" : "Activity"
      },
      "componentName" : "forceCommunity:recordHomeTabs",
      "id" : "0978b8ae-114f-4e53-ae19-d945dc010027",
      "renderPriority" : "NEUTRAL",
      "renditionMap" : { },
      "type" : "component"
    } ],
    "id" : "b820c1c5-c5b1-4d8b-92c8-9c780d90e6e4",
    "regionName" : "content",
    "type" : "region"
  }, {
    "id" : "3d685cb2-b371-48bf-9f1b-e680ccc15a55",
    "regionName" : "footer",
    "type" : "region"
  }, {
    "components" : [ {
      "componentAttributes" : {
        "customHeadTags" : "",
        "description" : "",
        "title" : "{!Record._Object}: {!Record._Title}"
      },
      "componentName" : "forceCommunity:seoAssistant",
      "id" : "9b776e2f-8bb7-4b90-8efb-520b84a85158",
      "renditionMap" : { },
      "type" : "component"
    } ],
    "id" : "0ac0571a-913f-4f47-9237-b38a3b728e3f",
    "regionName" : "sfdcHiddenRegion",
    "type" : "region"
  } ],
  "themeLayoutType" : "Inner",
  "type" : "view",
  "viewType" : "detail"
}